CHANGES.rst
CONTRIBUTORS.rst
DEVELOP.rst
DEVELOP_THEME.rst
LICENSE.rst
MANIFEST.in
README.rst
setup.cfg
setup.py
docs/LICENSE.GPL
docs/LICENSE.rst
docs/index.rst
src/sandia/__init__.py
src/sandia.conferencetheme.egg-info/PKG-INFO
src/sandia.conferencetheme.egg-info/SOURCES.txt
src/sandia.conferencetheme.egg-info/dependency_links.txt
src/sandia.conferencetheme.egg-info/entry_points.txt
src/sandia.conferencetheme.egg-info/namespace_packages.txt
src/sandia.conferencetheme.egg-info/not-zip-safe
src/sandia.conferencetheme.egg-info/requires.txt
src/sandia.conferencetheme.egg-info/top_level.txt
src/sandia/conferencetheme/__init__.py
src/sandia/conferencetheme/configure.zcml
src/sandia/conferencetheme/interfaces.py
src/sandia/conferencetheme/setuphandlers.py
src/sandia/conferencetheme/testing.py
src/sandia/conferencetheme/browser/__init__.py
src/sandia/conferencetheme/browser/configure.zcml
src/sandia/conferencetheme/browser/overrides/.gitkeep
src/sandia/conferencetheme/browser/static/.gitkeep
src/sandia/conferencetheme/locales/sandia.conferencetheme.pot
src/sandia/conferencetheme/locales/update.sh
src/sandia/conferencetheme/profiles/default/browserlayer.xml
src/sandia/conferencetheme/profiles/default/metadata.xml
src/sandia/conferencetheme/profiles/default/registry.xml
src/sandia/conferencetheme/profiles/default/theme.xml
src/sandia/conferencetheme/profiles/uninstall/browserlayer.xml
src/sandia/conferencetheme/profiles/uninstall/theme.xml
src/sandia/conferencetheme/tests/__init__.py
src/sandia/conferencetheme/tests/test_robot.py
src/sandia/conferencetheme/tests/test_setup.py
src/sandia/conferencetheme/tests/robot/test_example.robot
src/sandia/conferencetheme/theme/backend.xml
src/sandia/conferencetheme/theme/barceloneta-apple-touch-icon-114x114-precomposed.png
src/sandia/conferencetheme/theme/barceloneta-apple-touch-icon-144x144-precomposed.png
src/sandia/conferencetheme/theme/barceloneta-apple-touch-icon-57x57-precomposed.png
src/sandia/conferencetheme/theme/barceloneta-apple-touch-icon-72x72-precomposed.png
src/sandia/conferencetheme/theme/barceloneta-apple-touch-icon-precomposed.png
src/sandia/conferencetheme/theme/barceloneta-apple-touch-icon.png
src/sandia/conferencetheme/theme/barceloneta-favicon.ico
src/sandia/conferencetheme/theme/index.html
src/sandia/conferencetheme/theme/manifest.cfg
src/sandia/conferencetheme/theme/package.json
