Metadata-Version: 2.1
Name: sandia.conferencetheme
Version: 1.0a3
Summary: A theme add-on for Plone
Home-page: https://pypi.python.org/pypi/sandia.conferencetheme
Author: T. Kim Nguyen
Author-email: kim@sixfeetup.com
License: GPL version 2
Keywords: Python Plone
Platform: UNKNOWN
Classifier: Environment :: Web Environment
Classifier: Framework :: Plone
Classifier: Framework :: Plone :: 5.2
Classifier: Programming Language :: Python
Classifier: Programming Language :: Python :: 2.7
Classifier: Operating System :: OS Independent
Classifier: License :: OSI Approved :: GNU General Public License v2 (GPLv2)
Provides-Extra: test
